README.md
setup.py
tnp/__init__.py
tnp/env.py
tnp/init.py
tnp/pipe.py
tnp/program.py
tnp/secret.py
tnp/server.py
tnp.egg-info/PKG-INFO
tnp.egg-info/SOURCES.txt
tnp.egg-info/dependency_links.txt
tnp.egg-info/entry_points.txt
tnp.egg-info/not-zip-safe
tnp.egg-info/requires.txt
tnp.egg-info/top_level.txt