Metadata-Version: 2.1
Name: tnp
Version: 0.1.1
Summary: Practical pipelining on GCP.
Home-page: https://github.com/timlyrics/tnp
Author: Shaoqing Tan
Author-email: tansq7@gmail.com
License: MIT
Platform: UNKNOWN
